<?xml version = '1.0' encoding = 'UTF-8'?>
<FKIndexAssociation class="oracle.dbtools.crest.model.design.relational.FKIndexAssociation" directorySegmentName="seg_0" id="506C66A3-3937-1F4F-A1C4-DDD3ABDCF205" containerWithKeyObject="C30D8014-A906-1E5C-8292-237774A95F2D" localFKIndex="DDD1D138-918D-FD69-5345-B2DAAB0A0E0B" name="Pedido_Factura_FK">
<createdBy>carlos</createdBy>
<createdTime>2021-04-27 15:03:52 UTC</createdTime>
<ownerDesignName>ModeloGear</ownerDesignName>
<referredTableLongName>Factura</referredTableLongName>
<deleteRule>NO ACTION</deleteRule>
<referredTableID>9D5E6DA1-6412-7573-B256-B13389D9ABE1</referredTableID>
<keyObject>4792A482-0857-8CD9-A25C-ABD7D3C28E33</keyObject>
<referredKeyID>4792A482-0857-8CD9-A25C-ABD7D3C28E33</referredKeyID>
<mandatory>true</mandatory>
<refColNames>codigo</refColNames>
<transferable>true</transferable>
<rely>false</rely>
<columnDependencyConstraintGenerateInDDL>true</columnDependencyConstraintGenerateInDDL>
</FKIndexAssociation>
